gradscope/__init__.py
gradscope/alerts.py
gradscope/cli.py
gradscope/config.py
gradscope/diff.py
gradscope/export.py
gradscope/monitor.py
gradscope/registry.py
gradscope/report.py
gradscope/server.py
gradscope/storage.py
gradscope/utils.py
gradscope-0.1.0.dist-info/METADATA
gradscope-0.1.0.dist-info/WHEEL
gradscope-0.1.0.dist-info/entry_points.txt
gradscope-0.1.0.dist-info/top_level.txt
gradscope-0.1.0.dist-info/RECORD
