Metadata-Version: 2.4
Name: gradscope
Version: 0.1.0
Summary: Gradient and training anomaly monitoring for PyTorch and TensorFlow
Author: Prabhnoor Singh
License: MIT
Project-URL: Homepage, https://github.com/your-org/gradscope
Project-URL: Source, https://github.com/your-org/gradscope
Requires-Python: >=3.9
Requires-Dist: typing-extensions; python_version < "3.11"
Provides-Extra: server
Requires-Dist: fastapi; extra == "server"
Requires-Dist: uvicorn; extra == "server"
Provides-Extra: system
Requires-Dist: psutil; extra == "system"
